{
  "nodes": [
    {
      "node": 0,
      "name": "Backbone JS"
    },
    {
      "node": 1,
      "name": "Marionette JS"
    },
    {
      "node": 2,
      "name": "Node JS"
    },
    {
      "node": 3,
      "name": "Swift"
    },
    {
      "node": 4,
      "name": "Objective-C"
    },
    {
      "node": 5,
      "name": "Xcode"
    },
    {
      "node": 6,
      "name": "Cordova"
    },
    {
      "node": 7,
      "name": "Android"
    },
    {
      "node": 8,
      "name": ""
    }
  ],
  "links": [
    {
      "source": 0,
      "target": 8,
      "value": 40
    },
    {
      "source": 1,
      "target": 8,
      "value": 25
    },
    {
      "source": 2,
      "target": 8,
      "value": 80
    },
    {
      "source": 8,
      "target": 3,
      "value": 1
    },
    {
      "source": 8,
      "target": 4,
      "value": 16
    },
    {
      "source": 8,
      "target": 5,
      "value": 6
    },
    {
      "source": 8,
      "target": 6,
      "value": 60
    },
    {
      "source": 8,
      "target": 7,
      "value": 40
    }
  ]
}